__init__.py
encoding.py
paillier.py
util.py
paillier_numpy-0.0.2.dist-info/LICENSE
paillier_numpy-0.0.2.dist-info/METADATA
paillier_numpy-0.0.2.dist-info/WHEEL
paillier_numpy-0.0.2.dist-info/top_level.txt
paillier_numpy-0.0.2.dist-info/RECORD
