Metadata-Version: 2.1
Name: paillier_numpy
Version: 0.0.2
Summary: 你吃辣条舔袋吗
Author-email: Galloroc <1176651368@qq.com>
Project-URL: Homepage, https://github.com/Galloroc1/paillier
Project-URL: Issues, https://github.com/Galloroc1/paillier/issues
Classifier: Programming Language :: Python :: 3
Classifier: License :: OSI Approved :: MIT License
Classifier: Operating System :: OS Independent
Requires-Python: >=3.8
License-File: LICENSE
